{"q+DBL6Ip/DUrNNhuYzaAOQ==":"mbr.jpg","gsjYRdHRUVZKKoL5D2DVIg==":"mbr.jpeg","Jvd/Hv+E6dzGxsxf1OSMGw==":"mbr-1.jpg","Rkh6VN1geuklqasa+Hps8w==":"mbr-2.jpg","OgtCKla7ZhzAplY/dXMFRQ==":"mbr-3.jpg","7cAX25vTViPzsEpxKtfgnw==":"mbr-4.jpg","Bzg68IuBcRh9sFO8XLZmEQ==":"mbr-5.jpg","3L8x5ialuZVROWzapuz4nA==":"mbr-6.jpg","5Yxz1Ro3xgEvJK27QZYsvA==":"mbr-1.jpeg","orRrDp0O7uYYPUWXMASTrg==":"mbr-2.jpeg","hNnJ/ah4jJ+gnKLIjKCM+Q==":"mbr-3.jpeg","8lvp9ISHPOav0iH8GHzE5A==":"mbr-596x397.jpg","kaaZrDFsJPHjOi+rzSiDVQ==":"titlecard24.png","tav17loUWTbkI+OlzhZfVQ==":"logo-crittercrossfire.png","F/jZSb9dwjvny85uHU7MPw==":"titlecard25.png","dUeWEKzu1vk0wc3GK1ZMUw==":"logo-crittercrossfire-1.png","MHV4KIzPG39XyVUCFCvfCA==":"titlecard26.png","LAhOV0gqjgdMb31aBOdiAg==":"logo-crittercrossfire-2.png","nUMN84xyP+yOZscdlYbqog==":"logo-crittercrossfire-3.png","dtY8xaOZtO7vm17JKHmefg==":"logo-crittercrossfire-4.png","zjkuwzzRKKQSRREHOj9gTA==":"mbr-6.jpg","Fx2Kgv4qRP2zG0YZxF5Wag==":"giphy.gif","ouVlBUw7HmfK74brxoOU0g==":"gungun.gif","zz2hKEq+9hcgo7X/gFgu/w==":"bounceammo.gif","ffx3nAqGz3ScPZbwyrFlRw==":"grenade.gif","zQGfaq921JzNFVdVuesZjA==":"firework.gif","h+QraRslHd6XyNiy7JLqQQ==":"homing.gif","j6LiKL+Rq9V1U3vsliH2fQ==":"laser.gif","IKYMuWJeiql/U6T5fpo4jw==":"towardscamera.gif","HoF5pTCUDUKwPN1cGp/1VA==":"screenshot31.png","TojNcWQSJDRaEaVuFzeYNQ==":"screenshot32.png","tMx52BCIcxC40JBo3LFC6Q==":"screenshot33.png"}